wygr/__init__.py
wygr/agents/medical_agent.py
wygr/agents/teaching_agent.py
wygr/agents/travel_planner.py
wygr/app/streamlit_app.py
wygr/memory/basic_memory.py
wygr/models/openai.py
wygr/prompts/prompts.py
wygr/tools/__init__.py
wygr/tools/base_tool.py
wygr/tools/generating_syllabus.py
wygr/tools/ititnerary_tools.py
wygr/tools/prebuilt_tools.py
wygr/tools/raw_functions.py
wygr/utils/helpers.py
wygr-0.0.9.dist-info/METADATA
wygr-0.0.9.dist-info/WHEEL
wygr-0.0.9.dist-info/licenses/LICENSE
wygr-0.0.9.dist-info/RECORD
