Metadata-Version: 2.4
Name: wygr
Version: 0.0.9
Summary: This is a Travel Planner App built with Streamlit that generates personalized travel itineraries based on user input
Project-URL: Homepage, https://github.com/saikrisnaa/wygr
Project-URL: Issues, https://github.com/saikrisnaa/wygr
Author-email: sai <yenishettysai@gmail.com>
License-File: LICENSE
Classifier: License :: OSI Approved :: GNU General Public License v3 (GPLv3)
Classifier: Operating System :: OS Independent
Classifier: Programming Language :: Python :: 3
Requires-Python: >=3.0
